gapandas4/__init__.py
gapandas4/gapandas4.py
gapandas4-0.3.dist-info/LICENSE.txt
gapandas4-0.3.dist-info/METADATA
gapandas4-0.3.dist-info/WHEEL
gapandas4-0.3.dist-info/top_level.txt
gapandas4-0.3.dist-info/RECORD
