Metadata-Version: 2.1
Name: gapandas4
Version: 0.3
Summary: GAPandas4 is a Python package for accessing the Google Analytics Data API for GA4 using Pandas
Home-page: https://github.com/practicaldatascience/gapandas4
Author: Matt Clarke
Author-email: matt@practicaldatascience.co.uk
License: MIT
Download-URL: https://github.com/practicaldatascience/gapandas4/archive/master.zip
Keywords: python,google analytics,ga,pandas,universal analytics,gapandas,ga4
Platform: UNKNOWN
Classifier: Development Status :: 3 - Alpha
Classifier: Intended Audience :: Developers
Classifier: Topic :: Software Development :: Libraries :: Python Modules
Classifier: License :: OSI Approved :: MIT License
Classifier: Programming Language :: Python :: 3.6
Requires-Dist: google-analytics-data
Requires-Dist: pandas
